[
    {
        "name": "Albanian",
        "code": "sq"
    },
    {
        "name": "Arabic",
        "code": "ar"
    },
    {
        "name": "Armenian",
        "code": "hy"
    },
    {
        "name": "Awadhi",
        "code": "awa"
    },
    {
        "name": "Azerbaijani",
        "code": "az"
    },
    {
        "name": "Bashkir",
        "code": "ba"
    },
    {
        "name": "Basque",
        "code": "eu"
    },
    {
        "name": "Belarusian",
        "code": "be"
    },
    {
        "name": "Bengali",
        "code": "bn"
    },
    {
        "name": "Bhojpuri",
        "code": "bho"
    },
    {
        "name": "Bosnian",
        "code": "bs"
    },
    {
        "name": "Brazilian Portuguese",
        "code": "pt-BR"
    },
    {
        "name": "Bulgarian",
        "code": "bg"
    },
    {
        "name": "Cantonese (Yue)",
        "code": "yue"
    },
    {
        "name": "Catalan",
        "code": "ca"
    },
    {
        "name": "Chhattisgarhi",
        "code": "hne"
    },
    {
        "name": "Chinese",
        "code": "zh"
    },
    {
        "name": "Croatian",
        "code": "hr"
    },
    {
        "name": "Czech",
        "code": "cs"
    },
    {
        "name": "Danish",
        "code": "da"
    },
    {
        "name": "Dogri",
        "code": "doi"
    },
    {
        "name": "Dutch",
        "code": "nl"
    },
    {
        "name": "English",
        "code": "en"
    },
    {
        "name": "Estonian",
        "code": "et"
    },
    {
        "name": "Faroese",
        "code": "fo"
    },
    {
        "name": "Finnish",
        "code": "fi"
    },
    {
        "name": "French",
        "code": "fr"
    },
    {
        "name": "Galician",
        "code": "gl"
    },
    {
        "name": "Georgian",
        "code": "ka"
    },
    {
        "name": "German",
        "code": "de"
    },
    {
        "name": "Greek",
        "code": "el"
    },
    {
        "name": "Gujarati",
        "code": "gu"
    },
    {
        "name": "Haryanvi",
        "code": "bgc"
    },
    {
        "name": "Hindi",
        "code": "hi"
    },
    {
        "name": "Hungarian",
        "code": "hu"
    },
    {
        "name": "Indonesian",
        "code": "id"
    },
    {
        "name": "Irish",
        "code": "ga"
    },
    {
        "name": "Italian",
        "code": "it"
    },
    {
        "name": "Japanese",
        "code": "ja"
    },
    {
        "name": "Javanese",
        "code": "jv"
    },
    {
        "name": "Kannada",
        "code": "kn"
    },
    {
        "name": "Kashmiri",
        "code": "ks"
    },
    {
        "name": "Kazakh",
        "code": "kk"
    },
    {
        "name": "Konkani",
        "code": "kok"
    },
    {
        "name": "Korean",
        "code": "ko"
    },
    {
        "name": "Kyrgyz",
        "code": "ky"
    },
    {
        "name": "Latvian",
        "code": "lv"
    },
    {
        "name": "Lithuanian",
        "code": "lt"
    },
    {
        "name": "Macedonian",
        "code": "mk"
    },
    {
        "name": "Maithili",
        "code": "mai"
    },
    {
        "name": "Malay",
        "code": "ms"
    },
    {
        "name": "Maltese",
        "code": "mt"
    },
    {
        "name": "Mandarin",
        "code": "zh"
    },
    {
        "name": "Mandarin Chinese",
        "code": "zh"
    },
    {
        "name": "Marathi",
        "code": "mr"
    },
    {
        "name": "Marwari",
        "code": "mwr"
    },
    {
        "name": "Min Nan",
        "code": "nan"
    },
    {
        "name": "Moldovan",
        "code": "mo"
    },
    {
        "name": "Mongolian",
        "code": "mn"
    },
    {
        "name": "Montenegrin",
        "code": "srp"
    },
    {
        "name": "Nepali",
        "code": "ne"
    },
    {
        "name": "Norwegian",
        "code": "no"
    },
    {
        "name": "Oriya",
        "code": "or"
    },
    {
        "name": "Pashto",
        "code": "ps"
    },
    {
        "name": "Persian (Farsi)",
        "code": "fa"
    },
    {
        "name": "Polish",
        "code": "pl"
    },
    {
        "name": "Portuguese",
        "code": "pt"
    },
    {
        "name": "Punjabi",
        "code": "pa"
    },
    {
        "name": "Rajasthani",
        "code": "raj"
    },
    {
        "name": "Romanian",
        "code": "ro"
    },
    {
        "name": "Russian",
        "code": "ru"
    },
    {
        "name": "Sanskrit",
        "code": "sa"
    },
    {
        "name": "Santali",
        "code": "sat"
    },
    {
        "name": "Serbian",
        "code": "sr"
    },
    {
        "name": "Sindhi",
        "code": "sd"
    },
    {
        "name": "Sinhala",
        "code": "si"
    },
    {
        "name": "Slovak",
        "code": "sk"
    },
    {
        "name": "Slovene",
        "code": "sl"
    },
    {
        "name": "Slovenian",
        "code": "sl"
    },
    {
        "name": "Spanish",
        "code": "es"
    },
    {
        "name": "Swahili",
        "code": "sw"
    },
    {
        "name": "Swedish",
        "code": "sv"
    },
    {
        "name": "Tajik",
        "code": "tg"
    },
    {
        "name": "Tamil",
        "code": "ta"
    },
    {
        "name": "Tatar",
        "code": "tt"
    },
    {
        "name": "Telugu",
        "code": "te"
    },
    {
        "name": "Thai",
        "code": "th"
    },
    {
        "name": "Turkish",
        "code": "tr"
    },
    {
        "name": "Turkmen",
        "code": "tk"
    },
    {
        "name": "Ukrainian",
        "code": "uk"
    },
    {
        "name": "Urdu",
        "code": "ur"
    },
    {
        "name": "Uzbek",
        "code": "uz"
    },
    {
        "name": "Vietnamese",
        "code": "vi"
    },
    {
        "name": "Welsh",
        "code": "cy"
    },
    {
        "name": "Wu",
        "code": "wuu"
    }
]
